byebye_docs_mcp/__init__.py
byebye_docs_mcp/__main__.py
byebye_docs_mcp/server.py
byebye_docs_mcp/core/__init__.py
byebye_docs_mcp/core/diff_engine.py
byebye_docs_mcp/core/sync_manager.py
byebye_docs_mcp/extractors/__init__.py
byebye_docs_mcp/extractors/api_extractor.py
byebye_docs_mcp/extractors/entity_extractor.py
byebye_docs_mcp/models/__init__.py
byebye_docs_mcp/models/code_elements.py
byebye_docs_mcp/models/diff_result.py
byebye_docs_mcp/parsers/__init__.py
byebye_docs_mcp/parsers/base.py
byebye_docs_mcp/parsers/python_parser.py
byebye_docs_mcp/parsers/typescript_parser.py
byebye_docs_mcp-0.2.1.dist-info/METADATA
byebye_docs_mcp-0.2.1.dist-info/WHEEL
byebye_docs_mcp-0.2.1.dist-info/entry_points.txt
byebye_docs_mcp-0.2.1.dist-info/RECORD
