Metadata-Version: 2.4
Name: byebye-docs-mcp
Version: 0.2.1
Summary: MCP server for AI-first development design document templates
Project-URL: Homepage, https://github.com/pon-tanuki/byebye-docs
Project-URL: Repository, https://github.com/pon-tanuki/byebye-docs
Project-URL: Documentation, https://github.com/pon-tanuki/byebye-docs/blob/main/mcp-server/README.md
Project-URL: Issues, https://github.com/pon-tanuki/byebye-docs/issues
Author: pon-tanuki
License-Expression: MIT
Keywords: ai,claude,code-sync,design-docs,documentation,mcp
Classifier: Development Status :: 4 - Beta
Classifier: Intended Audience :: Developers
Classifier: License :: OSI Approved :: MIT License
Classifier: Programming Language :: Python :: 3
Classifier: Programming Language :: Python :: 3.10
Classifier: Programming Language :: Python :: 3.11
Classifier: Programming Language :: Python :: 3.12
Classifier: Programming Language :: Python :: 3.13
Classifier: Topic :: Software Development :: Documentation
Classifier: Topic :: Software Development :: Libraries :: Python Modules
Requires-Python: >=3.10
Requires-Dist: jsonschema>=4.0
Requires-Dist: mcp>=1.0.0
Requires-Dist: pyyaml>=6.0
Provides-Extra: dev
Requires-Dist: pytest-asyncio>=0.23; extra == 'dev'
Requires-Dist: pytest>=8.0; extra == 'dev'
Requires-Dist: ruff>=0.1; extra == 'dev'
